Metadata-Version: 2.1
Name: phx-filters-django
Version: 3.1.0
Summary: Extends phx-filters, adding filters useful for Django applications.
Author-email: Phoenix Zerin <phx@phx.nz>
License: MIT License
Project-URL: Documentation, https://filters.readthedocs.io/en/latest/extension_filters.html#django-filters
Project-URL: Changelog, https://github.com/todofixthis/filters-django/releases
Project-URL: Issues, https://github.com/todofixthis/filters-django/issues
Project-URL: Repository, https://github.com/todofixthis/filters-django
Keywords: data validation,django,filters,extension filters
Classifier: Development Status :: 5 - Production/Stable
Classifier: Intended Audience :: Developers
Classifier: License :: OSI Approved :: MIT License
Classifier: Programming Language :: Python :: 3
Classifier: Programming Language :: Python :: 3.12
Classifier: Programming Language :: Python :: 3.11
Classifier: Programming Language :: Python :: 3.10
Classifier: Topic :: Software Development :: Libraries :: Python Modules
Classifier: Topic :: Text Processing :: Filters
Requires-Python: >=3.10
License-File: LICENCE.txt
Requires-Dist: phx-filters >=3.4.0
Requires-Dist: Django >=4.0
Provides-Extra: build-system
Requires-Dist: build ; extra == 'build-system'
Requires-Dist: twine ; extra == 'build-system'
Provides-Extra: test-runner
Requires-Dist: tox ; extra == 'test-runner'
